Workbook

Sheet Kalkulation
B2: Immobilien-Rechner: Kaufen & Vermieten (Buy & Hold) | S2: Legende / Notizen
B3: Vergleich monatliche Einnahmen vs. Ausgaben → Cashflow & Rendite als Kaufentscheidung | S3: Hellblau = Eingabefeld • Schwarz = berechnet • Grün = Ergebnis
B5: 1. Ankauf (€/m² in Spalte E) | G5: 4. Laufende Kosten (nicht umlagefähig, p.M.) | S5: So nutzt du den Rechner:
B6: Kaufpreis | D6: 180000 | E6: =D6/D7 | G6: nicht uml. Hausgeld | I6: 50 | S6: 1. Trage nur die HELLBLAUEN Felder ein (Kaufpreis, Fläche, Zins, Miete ...).
B7: Wohnfläche | D7: 60 | E7: m² | G7: Instandhaltung €/m²/Jahr | H7: 10 | I7: =H7*D7/12 | S7: 2. Alles andere rechnet sich automatisch.
B8: Notar + Grundbuch | C8: 0.015 | D8: =D6*C8 | E8: =D8/D7 | G8: Verwaltung (extern) p.M. | I8: 25 | S8: 3. Schau auf Block 5 (Cashflow) und 6 (Renditen) – das ist deine Kaufentscheidung.
B9: Makler | C9: 0.0357 | D9: =D6*C9 | E9: =D9/D7 | G9: Mietausfallwagnis | H9: 0.03 | I9: =D29*H9
B10: Grunderwerbsteuer | C10: 0.065 | D10: =D6*C10 | E10: =D10/D7 | G10: Summe lfd. Kosten p.M. | I10: =SUM(I6:I9) | S10: Kapitaldienst = Zins + Tilgung. Das ist deine echte Monatsrate an die Bank.
B11: Kaufnebenkosten | D11: =SUM(D8:D10) | E11: =D11/D7 | G11: Summe lfd. Kosten p.a. | I11: =I10*12 | S11: Tilgung ist KEIN Verlust – du baust damit Eigenkapital/Vermögen auf (Block 6).
B12: Gesamtinvestition | D12: =D6+D11 | E12: =D12/D7
B13: Gebäudeanteil (für AfA) | C13: 0.8 | D13: =D6*C13 | E13: Gebäudewert | G13: 5. Cashflow (Einnahmen − Ausgaben) | S13: Cashflow vor Steuer = Kaltmiete − Rate − lfd. Kosten.
G14: Kaltmiete p.M. | I14: =D29 | S14: Positiver Cashflow = die Immobilie trägt sich selbst.
B15: 2. Finanzierung | G15: − Kapitaldienst (Zins+Tilgung) | I15: =-D22
B16: Finanzierungsquote | C16: 1 | D16: von Gesamtinvest. | G16: − lfd. Kosten | I16: =-I10 | S16: Steuer: oft entsteht durch Zinsen + AfA ein steuerlicher Verlust → Erstattung,
B17: Darlehenssumme | D17: =D12*C16 | G17: Cashflow VOR Steuer p.M. | I17: =I14+I15+I16 | S17: d.h. der Cashflow nach Steuer ist meist besser als vor Steuer.
B18: Eigenkapital | D18: =D12-D17 | G18: Cashflow vor Steuer p.a. | I18: =I17*12
B19: Sollzins p.a. | C19: 0.04 | G19: AfA p.a. (2% Gebäude) | H19: 0.02 | I19: =D13*H19 | S19: Bruttomietrendite ab ~4-5% gilt als interessant (lagenabhängig).
B20: anfängl. Tilgung p.a. | C20: 0.02 | G20: Grenzsteuersatz | H20: 0.42 | S20: Kaufpreisfaktor < 25x ist solide, < 20x günstig.
B21: Annuität p.a. | D21: =D17*(C19+C20) | G21: steuerl. Ergebnis p.a. | I21: =D30-D23*12-I19-I11
B22: Annuität p.M. (Kapitaldienst) | D22: =D21/12 | G22: Steuer p.a. (+Last / −Erstattung) | I22: =I21*H20 | S22: Block 8: Wie ändern sich Cashflow & Rendite, wenn du den Preis drückst?
B23: davon Zins p.M. (Jahr 1) | D23: =D17*C19/12 | G23: Cashflow NACH Steuer p.a. | I23: =I18-I22
B24: davon Tilgung p.M. | D24: =D22-D23 | G24: Cashflow nach Steuer p.M. | I24: =I23/12 | S24: Hinweis: vereinfachtes Modell, keine Steuer-/Anlageberatung.
B26: 3. Mieteinnahmen | G26: 6. Renditen & Kennzahlen
B27: Kaltmiete €/m² | C27: 9 | G27: Bruttomietrendite | I27: =D30/D6
B28: Stellplatz / Sonstiges p.M. | D28: 0 | G28: Nettomietrendite | I28: =(D30-I11)/D12
B29: Kaltmiete p.M. | D29: =C27*D7+D28 | G29: Eigenkapitalrendite (n. St.) | I29: =IF(D18<=0,"n/a (Vollfin.)",(I23+D24*12)/D18)
B30: Kaltmiete p.a. | D30: =D29*12 | G30: Kaufpreisfaktor | I30: =D6/D30
G31: Tilgung baut Vermögen p.a. | I31: =D24*12
G33: 7. Bewertung
G34: Cashflow vor Steuer | I34: =IF(I17>=50,"positiv ✓",IF(I17>=0,"knapp ±","negativ ✗"))
G35: Bruttomietrendite | I35: =IF(I27>=0.045,"gut ✓",IF(I27>=0.035,"ok ±","niedrig ✗"))
G36: Gesamturteil | I36: =IF(AND(I17>=0,I27>=0.04),"Kaufen prüfen ✓",IF(I17>=-100,"Grenzfall – verhandeln","Eher nein ✗"))
B39: 8. Szenario: Kaufpreis-Verhandlung
B40: Discount | C40: Kaufpreis | D40: Gesamtinvest. | E40: Darlehen | F40: Annuität p.M. | G40: CF vor St. p.M. | H40: Bruttorendite | I40: Nettorendite
B41: 0 | C41: =$D$6*(1-B41) | D41: =C41*(1+$C$8+$C$9+$C$10) | E41: =D41*$C$16 | F41: =E41*($C$19+$C$20)/12 | G41: =$D$29-F41-$I$10 | H41: =$D$30/C41 | I41: =($D$30-$I$11)/D41
B42: 0.05 | C42: =$D$6*(1-B42) | D42: =C42*(1+$C$8+$C$9+$C$10) | E42: =D42*$C$16 | F42: =E42*($C$19+$C$20)/12 | G42: =$D$29-F42-$I$10 | H42: =$D$30/C42 | I42: =($D$30-$I$11)/D42
B43: 0.1 | C43: =$D$6*(1-B43) | D43: =C43*(1+$C$8+$C$9+$C$10) | E43: =D43*$C$16 | F43: =E43*($C$19+$C$20)/12 | G43: =$D$29-F43-$I$10 | H43: =$D$30/C43 | I43: =($D$30-$I$11)/D43
B44: 0.15 | C44: =$D$6*(1-B44) | D44: =C44*(1+$C$8+$C$9+$C$10) | E44: =D44*$C$16 | F44: =E44*($C$19+$C$20)/12 | G44: =$D$29-F44-$I$10 | H44: =$D$30/C44 | I44: =($D$30-$I$11)/D44
B45: 0.2 | C45: =$D$6*(1-B45) | D45: =C45*(1+$C$8+$C$9+$C$10) | E45: =D45*$C$16 | F45: =E45*($C$19+$C$20)/12 | G45: =$D$29-F45-$I$10 | H45: =$D$30/C45 | I45: =($D$30-$I$11)/D45

Sheet Projektion
B2: 20-Jahres-Projektion: Tilgungsplan, Cashflow & Zins-Sensitivität
B3: Annuitätendarlehen. Werte ziehen aus Blatt 'Kalkulation'. Hellblau = anpassbar.
B5: Annahmen | E5: Herleitung (aus Kalkulation)
B6: Mietsteigerung p.a. | C6: 0.015 | E6: Darlehen | G6: =Kalkulation!D17
B7: Kostensteigerung p.a. | C7: 0.02 | E7: Sollzins (Phase 1) | G7: =Kalkulation!C19
B8: Zinsbindung (Jahre) | C8: 10 | E8: anf. Tilgung | G8: =Kalkulation!C20
B9: Anschlusszins p.a. | C9: 0.05 | E9: Annuität Phase 1 p.a. | G9: =G6*(G7+G8)
E10: Restschuld bei Anschluss | G10: =G6*(1+G7)^C8-G9*((1+G7)^C8-1)/G7
E11: Annuität Phase 2 p.a. | G11: =G10*(C9+G8)
A13: Tilgungsplan & Cashflow (20 Jahre)
A14: Jahr | B14: Restschuld Anfang | C14: Zinssatz | D14: Zins | E14: Tilgung | F14: Restschuld Ende | G14: Annuität | H14: Kaltmiete | I14: lfd. Kosten | J14: CF vor St. | K14: CF n. St. | L14: CF kumul. (n. St.)
A15: 1 | B15: =$G$6 | C15: =IF(A15<=$C$8,$G$7,$C$9) | D15: =B15*C15 | E15: =G15-D15 | F15: =MAX(0,B15-E15) | G15: =MIN(IF(A15<=$C$8,$G$9,$G$11),B15+D15) | H15: =Kalkulation!$D$30*(1+$C$6)^(A15-1) | I15: =Kalkulation!$I$11*(1+$C$7)^(A15-1) | J15: =H15-G15-I15 | K15: =J15-((H15-D15-Kalkulation!$I$19-I15)*Kalkulation!$H$20) | L15: =K15
A16: =A15+1 | B16: =F15 | C16: =IF(A16<=$C$8,$G$7,$C$9) | D16: =B16*C16 | E16: =G16-D16 | F16: =MAX(0,B16-E16) | G16: =MIN(IF(A16<=$C$8,$G$9,$G$11),B16+D16) | H16: =Kalkulation!$D$30*(1+$C$6)^(A16-1) | I16: =Kalkulation!$I$11*(1+$C$7)^(A16-1) | J16: =H16-G16-I16 | K16: =J16-((H16-D16-Kalkulation!$I$19-I16)*Kalkulation!$H$20) | L16: =L15+K16
A17: =A16+1 | B17: =F16 | C17: =IF(A17<=$C$8,$G$7,$C$9) | D17: =B17*C17 | E17: =G17-D17 | F17: =MAX(0,B17-E17) | G17: =MIN(IF(A17<=$C$8,$G$9,$G$11),B17+D17) | H17: =Kalkulation!$D$30*(1+$C$6)^(A17-1) | I17: =Kalkulation!$I$11*(1+$C$7)^(A17-1) | J17: =H17-G17-I17 | K17: =J17-((H17-D17-Kalkulation!$I$19-I17)*Kalkulation!$H$20) | L17: =L16+K17
A18: =A17+1 | B18: =F17 | C18: =IF(A18<=$C$8,$G$7,$C$9) | D18: =B18*C18 | E18: =G18-D18 | F18: =MAX(0,B18-E18) | G18: =MIN(IF(A18<=$C$8,$G$9,$G$11),B18+D18) | H18: =Kalkulation!$D$30*(1+$C$6)^(A18-1) | I18: =Kalkulation!$I$11*(1+$C$7)^(A18-1) | J18: =H18-G18-I18 | K18: =J18-((H18-D18-Kalkulation!$I$19-I18)*Kalkulation!$H$20) | L18: =L17+K18
A19: =A18+1 | B19: =F18 | C19: =IF(A19<=$C$8,$G$7,$C$9) | D19: =B19*C19 | E19: =G19-D19 | F19: =MAX(0,B19-E19) | G19: =MIN(IF(A19<=$C$8,$G$9,$G$11),B19+D19) | H19: =Kalkulation!$D$30*(1+$C$6)^(A19-1) | I19: =Kalkulation!$I$11*(1+$C$7)^(A19-1) | J19: =H19-G19-I19 | K19: =J19-((H19-D19-Kalkulation!$I$19-I19)*Kalkulation!$H$20) | L19: =L18+K19
A20: =A19+1 | B20: =F19 | C20: =IF(A20<=$C$8,$G$7,$C$9) | D20: =B20*C20 | E20: =G20-D20 | F20: =MAX(0,B20-E20) | G20: =MIN(IF(A20<=$C$8,$G$9,$G$11),B20+D20) | H20: =Kalkulation!$D$30*(1+$C$6)^(A20-1) | I20: =Kalkulation!$I$11*(1+$C$7)^(A20-1) | J20: =H20-G20-I20 | K20: =J20-((H20-D20-Kalkulation!$I$19-I20)*Kalkulation!$H$20) | L20: =L19+K20
A21: =A20+1 | B21: =F20 | C21: =IF(A21<=$C$8,$G$7,$C$9) | D21: =B21*C21 | E21: =G21-D21 | F21: =MAX(0,B21-E21) | G21: =MIN(IF(A21<=$C$8,$G$9,$G$11),B21+D21) | H21: =Kalkulation!$D$30*(1+$C$6)^(A21-1) | I21: =Kalkulation!$I$11*(1+$C$7)^(A21-1) | J21: =H21-G21-I21 | K21: =J21-((H21-D21-Kalkulation!$I$19-I21)*Kalkulation!$H$20) | L21: =L20+K21
A22: =A21+1 | B22: =F21 | C22: =IF(A22<=$C$8,$G$7,$C$9) | D22: =B22*C22 | E22: =G22-D22 | F22: =MAX(0,B22-E22) | G22: =MIN(IF(A22<=$C$8,$G$9,$G$11),B22+D22) | H22: =Kalkulation!$D$30*(1+$C$6)^(A22-1) | I22: =Kalkulation!$I$11*(1+$C$7)^(A22-1) | J22: =H22-G22-I22 | K22: =J22-((H22-D22-Kalkulation!$I$19-I22)*Kalkulation!$H$20) | L22: =L21+K22
A23: =A22+1 | B23: =F22 | C23: =IF(A23<=$C$8,$G$7,$C$9) | D23: =B23*C23 | E23: =G23-D23 | F23: =MAX(0,B23-E23) | G23: =MIN(IF(A23<=$C$8,$G$9,$G$11),B23+D23) | H23: =Kalkulation!$D$30*(1+$C$6)^(A23-1) | I23: =Kalkulation!$I$11*(1+$C$7)^(A23-1) | J23: =H23-G23-I23 | K23: =J23-((H23-D23-Kalkulation!$I$19-I23)*Kalkulation!$H$20) | L23: =L22+K23
A24: =A23+1 | B24: =F23 | C24: =IF(A24<=$C$8,$G$7,$C$9) | D24: =B24*C24 | E24: =G24-D24 | F24: =MAX(0,B24-E24) | G24: =MIN(IF(A24<=$C$8,$G$9,$G$11),B24+D24) | H24: =Kalkulation!$D$30*(1+$C$6)^(A24-1) | I24: =Kalkulation!$I$11*(1+$C$7)^(A24-1) | J24: =H24-G24-I24 | K24: =J24-((H24-D24-Kalkulation!$I$19-I24)*Kalkulation!$H$20) | L24: =L23+K24
A25: =A24+1 | B25: =F24 | C25: =IF(A25<=$C$8,$G$7,$C$9) | D25: =B25*C25 | E25: =G25-D25 | F25: =MAX(0,B25-E25) | G25: =MIN(IF(A25<=$C$8,$G$9,$G$11),B25+D25) | H25: =Kalkulation!$D$30*(1+$C$6)^(A25-1) | I25: =Kalkulation!$I$11*(1+$C$7)^(A25-1) | J25: =H25-G25-I25 | K25: =J25-((H25-D25-Kalkulation!$I$19-I25)*Kalkulation!$H$20) | L25: =L24+K25
A26: =A25+1 | B26: =F25 | C26: =IF(A26<=$C$8,$G$7,$C$9) | D26: =B26*C26 | E26: =G26-D26 | F26: =MAX(0,B26-E26) | G26: =MIN(IF(A26<=$C$8,$G$9,$G$11),B26+D26) | H26: =Kalkulation!$D$30*(1+$C$6)^(A26-1) | I26: =Kalkulation!$I$11*(1+$C$7)^(A26-1) | J26: =H26-G26-I26 | K26: =J26-((H26-D26-Kalkulation!$I$19-I26)*Kalkulation!$H$20) | L26: =L25+K26
A27: =A26+1 | B27: =F26 | C27: =IF(A27<=$C$8,$G$7,$C$9) | D27: =B27*C27 | E27: =G27-D27 | F27: =MAX(0,B27-E27) | G27: =MIN(IF(A27<=$C$8,$G$9,$G$11),B27+D27) | H27: =Kalkulation!$D$30*(1+$C$6)^(A27-1) | I27: =Kalkulation!$I$11*(1+$C$7)^(A27-1) | J27: =H27-G27-I27 | K27: =J27-((H27-D27-Kalkulation!$I$19-I27)*Kalkulation!$H$20) | L27: =L26+K27
... A34: =A33+1 | B34: =F33 | C34: =IF(A34<=$C$8,$G$7,$C$9) | D34: =B34*C34 | E34: =G34-D34 | F34: =MAX(0,B34-E34) | G34: =MIN(IF(A34<=$C$8,$G$9,$G$11),B34+D34) | H34: =Kalkulation!$D$30*(1+$C$6)^(A34-1) | I34: =Kalkulation!$I$11*(1+$C$7)^(A34-1) | J34: =H34-G34-I34 | K34: =J34-((H34-D34-Kalkulation!$I$19-I34)*Kalkulation!$H$20) | L34: =L33+K34
B37: Auf einen Blick
B38: Restschuld nach 10 Jahren | D38: =F24 | I38: → Zins-Sensitivität: oben den 'Anschlusszins' (C9) ändern.
B39: Restschuld nach 20 Jahren | D39: =F34 | I39: Ab Jahr 11 (nach Zinsbindung) rechnet die Tabelle mit dem neuen Zins.
B40: getilgt nach 20 J. | D40: =$G$6-F34 | I40: So siehst du, was bei steigenden Zinsen mit deinem Cashflow passiert.
B41: Cashflow kumuliert (20 J., n. St.) | D41: =L34
B42: Vermögenszuwachs 20 J. (Tilgung + CF kum.) | D42: =($G$6-F34)+L34 | I42: Hinweis: ohne Immobilien-Wertsteigerung gerechnet (konservativ).
